bossanova/__init__.py
bossanova/_backend.py
bossanova/_config.py
bossanova/_utils.py
bossanova/_parser/README.md
bossanova/_parser/__init__.py
bossanova/_parser/expr.py
bossanova/_parser/parser.py
bossanova/_parser/scanner.py
bossanova/_parser/token.py
bossanova/data/README.md
bossanova/data/__init__.py
bossanova/data/advertising.csv
bossanova/data/chickweight.csv
bossanova/data/credit.csv
bossanova/data/gammas.csv
bossanova/data/mtcars.csv
bossanova/data/penguins.csv
bossanova/data/poker.csv
bossanova/data/sleep.csv
bossanova/data/titanic.csv
bossanova/data/titanic_test.csv
bossanova/data/titanic_train.csv
bossanova/formula/README.md
bossanova/formula/__init__.py
bossanova/formula/contrasts.py
bossanova/formula/design.py
bossanova/formula/encoding.py
bossanova/formula/random_effects.py
bossanova/formula/transforms.py
bossanova/formula/z_matrix.py
bossanova/marginal/README.md
bossanova/marginal/__init__.py
bossanova/marginal/contrasts.py
bossanova/marginal/emm.py
bossanova/marginal/grid.py
bossanova/marginal/hypothesis.py
bossanova/marginal/joint_tests.py
bossanova/marginal/parser.py
bossanova/marginal/slopes.py
bossanova/models/README.md
bossanova/models/__init__.py
bossanova/models/display.py
bossanova/models/glm.py
bossanova/models/glmer.py
bossanova/models/latex.py
bossanova/models/lm.py
bossanova/models/lmer.py
bossanova/models/base/__init__.py
bossanova/models/base/mixed.py
bossanova/models/base/model.py
bossanova/ops/README.md
bossanova/ops/__init__.py
bossanova/ops/_array_ops.py
bossanova/ops/_get_ops.py
bossanova/ops/_jax_backend.py
bossanova/ops/_numpy_backend.py
bossanova/ops/batching.py
bossanova/ops/convergence.py
bossanova/ops/diagnostics.py
bossanova/ops/family.py
bossanova/ops/glm_fit.py
bossanova/ops/glmer_pirls.py
bossanova/ops/inference.py
bossanova/ops/initialization.py
bossanova/ops/lambda_builder.py
bossanova/ops/linalg.py
bossanova/ops/lmer_core.py
bossanova/ops/predict.py
bossanova/ops/rng.py
bossanova/ops/sparse_solver.py
bossanova-0.1.0.dev5.dist-info/METADATA
bossanova-0.1.0.dev5.dist-info/WHEEL
bossanova-0.1.0.dev5.dist-info/licenses/LICENSE
bossanova-0.1.0.dev5.dist-info/RECORD
