Metadata-Version: 2.4
Name: bossanova
Version: 0.1.0.dev5
Summary: Bridging statistical cultures with some jazz
Author: Eshin Jolly
License-Expression: MIT
License-File: LICENSE
Keywords: analysis,multi-level-modeling,regression,statistics
Classifier: Intended Audience :: Science/Research
Classifier: Operating System :: OS Independent
Classifier: Programming Language :: Python :: 3.11
Requires-Python: >=3.11
Requires-Dist: jax>=0.8.0
Requires-Dist: joblib>=1.3.0
Requires-Dist: nlopt>=2.9.0
Requires-Dist: numpy>=2.3.4
Requires-Dist: pandas>=2.0.0
Requires-Dist: polars>=1.0.0
Requires-Dist: pyarrow>=14.0.0
Requires-Dist: scikit-sparse>=0.4.16
Requires-Dist: scipy>=1.14.0
Requires-Dist: tqdm>=4.66.0
